llama_index/node_parser/docling/__init__.py
llama_index/node_parser/docling/base.py
llama_index_node_parser_docling-0.4.1.dist-info/METADATA
llama_index_node_parser_docling-0.4.1.dist-info/WHEEL
llama_index_node_parser_docling-0.4.1.dist-info/licenses/LICENSE
llama_index_node_parser_docling-0.4.1.dist-info/RECORD
