Metadata-Version: 2.4
Name: llama-index-node-parser-docling
Version: 0.4.1
Summary: llama-index node_parser docling integration
Author-email: Panos Vagenas <pva@zurich.ibm.com>
License-Expression: MIT
License-File: LICENSE
Requires-Python: ~=3.10
Requires-Dist: docling-core<3,>=2.18.0
Requires-Dist: llama-index-core<0.15,>=0.13.0
